sxy/__init__.py
sxy-0.0.1rc1.dist-info/licenses/LICENSE
sxy-0.0.1rc1.dist-info/METADATA
sxy-0.0.1rc1.dist-info/WHEEL
sxy-0.0.1rc1.dist-info/top_level.txt
sxy-0.0.1rc1.dist-info/RECORD
