Metadata-Version: 2.4
Name: sxy
Version: 0.0.1rc1
Summary: The sxy python project.
Author-email: "Elis K." <opensource@elis.cc>
License: MIT License
Project-URL: Homepage, https://github.com/el1s7/sxy
Keywords: sxy
Requires-Python: >=3.9
License-File: LICENSE
Dynamic: license-file
